fortnum/__init__.py
fortnum/fortnum.py
fortnum/utils.py
fortnum-0.0.8.dist-info/DESCRIPTION.rst
fortnum-0.0.8.dist-info/METADATA
fortnum-0.0.8.dist-info/RECORD
fortnum-0.0.8.dist-info/WHEEL
fortnum-0.0.8.dist-info/metadata.json
fortnum-0.0.8.dist-info/top_level.txt
